{
    "created": "2021-05-03T15:00:06.874753",
    "total_games": 106009,
    "timecontrol": {
        "slow": 106006,
        "blitz": 1,
        "rapid": 2
    },
    "EGTB_material_diff": {
        "KRPPvKRP": 37839,
        "KPPPvKPP": 5581,
        "KBPPvKBP": 5429,
        "KNPPvKNP": 4870,
        "KNPPvKBP": 4435,
        "KBPPvKNP": 3926,
        "KQPPvKQP": 3043,
        "KBPPvKRP": 3018,
        "KNPPvKRP": 1921,
        "KPPPvKBP": 1711,
        "KPPPvKNP": 1614,
        "KRPPvKRB": 1232,
        "KRBPvKRB": 1079,
        "KRPPvKRN": 1047,
        "KRBPvKRN": 799,
        "KRNPvKRN": 719,
        "KRNPvKRB": 685,
        "KBNPvKRP": 596,
        "KBPPPvKR": 431,
        "KRRPvKRR": 352,
        "KNPPPvKR": 318,
        "KRPPvKBN": 300,
        "KRBPvKQP": 274,
        "KPPPPvKR": 228,
        "KRNPvKQP": 197,
        "KBBPvKRP": 152,
        "KRBPvKRR": 148,
        "KRRPvKQP": 144,
        "KQPPvKRR": 141,
        "KPPPPvKB": 121,
        "KRPPPvKQ": 104,
        "KRNPvKRR": 99,
        "KRBPPvKQ": 98,
        "KBNPvKBN": 97,
        "KNNPvKRP": 96,
        "KQPPvKQB": 94,
        "KNPPvKBN": 84,
        "KBPPvKBN": 83,
        "KPPPPvKN": 80,
        "KBBPvKBN": 75,
        "KBNPvKRB": 73,
        "KRNPPvKQ": 71,
        "KQPPvKQN": 67,
        "KRPPvKNN": 49,
        "KNPPvKBB": 45,
        "KQBPvKQB": 41,
        "KQNPvKQB": 38,
        "KBPPvKBB": 38,
        "KRPPvKBB": 37,
        "KRBNvKQP": 34,
        "KQRPvKQR": 34,
        "KNPPvKNN": 34,
        "KQNPvKQN": 30,
        "KBNPvKBB": 28,
        "KBNPvKRN": 28,
        "KQBPvKQN": 26,
        "KBNPPvKQ": 25,
        "KBNPvKNN": 25,
        "KNNPvKBN": 25,
        "KQNPvKQR": 19,
        "KBBPvKRB": 17,
        "KQBPvKQR": 16,
        "KNNPvKRN": 13,
        "KBBPvKRN": 11,
        "KBPPvKNN": 10,
        "KRBBvKQP": 9,
        "KNNPvKRB": 9,
        "KBBPvKBB": 8,
        "KNNPvKNN": 7,
        "KNNPPvKQ": 5,
        "KBBNPvKQ": 5,
        "KRRPvKQB": 5,
        "KRNNvKQP": 5,
        "KBBPvKNN": 4,
        "KQQPvKQQ": 4,
        "KBBPPvKQ": 4,
        "KRBNvKRR": 4,
        "KNNPvKBB": 3,
        "KBBNvKQP": 3,
        "KRBNvKQB": 2,
        "KRNNvKRR": 2,
        "KBNNPvKQ": 2,
        "KBBNvKRB": 2,
        "KRBBvKRR": 1,
        "KBBNvKRR": 1,
        "KQRBvKQQ": 1,
        "KRRBvKQN": 1,
        "KNNNvKRN": 1,
        "KRRPvKQN": 1,
        "KRBNvKQN": 1,
        "KBNNvKQP": 1,
        "KRBPvKRP": 2279,
        "KRNPvKRP": 2147,
        "KRPPPvKR": 1508,
        "KNPPvKPP": 1481,
        "KPPPvKRP": 1467,
        "KBPPvKPP": 1138,
        "KRPPvKBP": 1012,
        "KRPPvKNP": 802,
        "KRPPvKQP": 715,
        "KBNPvKBP": 436,
        "KQPPPvKQ": 403,
        "KBPPPvKB": 315,
        "KBNPvKNP": 285,
        "KNPPPvKN": 269,
        "KBNPPvKR": 240,
        "KBBPvKBP": 211,
        "KQBPvKQP": 201,
        "KRPPvKRR": 169,
        "KBPPPvKN": 167,
        "KQNPvKQP": 156,
        "KNPPPvKB": 153,
        "KRRPvKRN": 130,
        "KPPPPvKP": 126,
        "KRRPvKRB": 125,
        "KRRPPvKQ": 109,
        "KQPPvKRB": 109,
        "KNNPvKNP": 101,
        "KBPPvKRB": 98,
        "KNPPvKRB": 92,
        "KNNPvKBP": 79,
        "KPPPvKBN": 78,
        "KNPPvKRN": 73,
        "KQPPvKRN": 73,
        "KBNPvKQP": 72,
        "KRBPvKBN": 69,
        "KBPPvKRN": 69,
        "KBBPvKNP": 53,
        "KNNPPvKR": 47,
        "KRBNPvKQ": 42,
        "KBPPPvKQ": 33,
        "KRNPvKBN": 32,
        "KBBPPvKR": 30,
        "KQPPvKQR": 28,
        "KNPPPvKQ": 26,
        "KRBNvKRB": 24,
        "KPPPvKNN": 24,
        "KRBPvKNN": 23,
        "KBBPvKQP": 19,
        "KRBPvKQB": 17,
        "KQRPvKQB": 17,
        "KRRBvKQP": 17,
        "KRBPvKBB": 16,
        "KRBNvKRN": 16,
        "KBBNvKRP": 14,
        "KQRPvKQN": 14,
        "KRNPvKBB": 13,
        "KRRBvKRR": 12,
        "KPPPvKBB": 11,
        "KRBBvKRB": 10,
        "KNNPvKQP": 10,
        "KRRNvKRR": 10,
        "KRBBPvKQ": 9,
        "KQBPvKRR": 9,
        "KRNPvKQN": 8,
        "KRNPvKQB": 7,
        "KBNNvKRP": 7,
        "KBNPvKRR": 7,
        "KRBPvKQN": 7,
        "KRNNPvKQ": 6,
        "KRRNvKQP": 6,
        "KRRPvKQR": 6,
        "KRNPvKNN": 6,
        "KRNNvKRB": 4,
        "KBBNvKBN": 3,
        "KQNPvKRR": 3,
        "KBNNvKNN": 3,
        "KQRBvKQR": 3,
        "KRBBvKRN": 2,
        "KNNPvKRR": 2,
        "KBBPvKRR": 2,
        "KBNNvKBN": 1,
        "KRNNvKRN": 1,
        "KRBNvKQR": 1,
        "KQNNvKQB": 1,
        "KBNNvKQB": 1,
        "KQRNvKQR": 1,
        "KBBNvKBB": 1,
        "KRPPvKPP": 676,
        "KRBPPvKR": 225,
        "KRNPPvKR": 225,
        "KQPPvKRP": 216,
        "KBNPvKPP": 111,
        "KRRPvKRP": 110,
        "KNPPPvKP": 100,
        "KBPPPvKP": 99,
        "KNPPvKQP": 84,
        "KRNPvKNP": 73,
        "KRBPvKNP": 70,
        "KBPPvKQP": 63,
        "KRBPvKBP": 57,
        "KRBNvKRP": 53,
        "KRNPvKBP": 53,
        "KQRPvKQP": 50,
        "KQBPPvKQ": 41,
        "KPPPvKRN": 40,
        "KPPPvKRB": 37,
        "KNNPvKPP": 34,
        "KBNPPvKB": 31,
        "KBNPPvKN": 31,
        "KRPPPvKN": 28,
        "KQNPPvKQ": 27,
        "KRNNvKRP": 25,
        "KPPPPvKQ": 22,
        "KNPPvKRR": 21,
        "KRPPPvKB": 17,
        "KRPPvKQB": 15,
        "KNNPPvKN": 12,
        "KBPPvKRR": 12,
        "KPPPPPvK": 11,
        "KQBPvKRB": 10,
        "KBBPvKPP": 9,
        "KRRBPvKQ": 9,
        "KBBPPvKB": 9,
        "KRRNPvKQ": 7,
        "KRBPvKQR": 7,
        "KBBNvKBP": 7,
        "KRPPvKQN": 6,
        "KRNPvKQR": 6,
        "KQBPvKQQ": 6,
        "KBNNvKBP": 5,
        "KNNPPvKB": 5,
        "KQBPvKRN": 5,
        "KBNNPvKR": 4,
        "KQNPvKRN": 4,
        "KQNNvKQP": 4,
        "KRBBvKRP": 3,
        "KQRPvKRR": 3,
        "KBBNPvKR": 3,
        "KQNPvKRB": 3,
        "KBNPvKQB": 2,
        "KQBBvKQP": 2,
        "KQPPvKNN": 2,
        "KQNPvKQQ": 2,
        "KBNPvKQN": 2,
        "KQBNvKQP": 2,
        "KBBPPvKN": 2,
        "KQQPvKQR": 1,
        "KQRNvKQN": 1,
        "KBNNvKNP": 1,
        "KNNPvKQN": 1,
        "KNNPvKQB": 1,
        "KQPPvKBN": 1,
        "KBBNvKNP": 1,
        "KQPPvKBB": 1,
        "KPPPvKQP": 129,
        "KRPPPvKP": 101,
        "KRNPvKPP": 62,
        "KRBPvKPP": 49,
        "KQPPvKNP": 47,
        "KBNPPvKP": 34,
        "KQPPvKBP": 32,
        "KRRPPvKR": 30,
        "KRPPvKQR": 20,
        "KRNPPvKN": 18,
        "KRBNPvKR": 18,
        "KQPPvKQQ": 16,
        "KQBPvKRP": 16,
        "KQPPPvKR": 14,
        "KRBPPvKB": 12,
        "KQNPvKRP": 11,
        "KPPPvKRR": 10,
        "KRBPPvKN": 9,
        "KRRPvKNP": 9,
        "KBPPPPvK": 8,
        "KQRPPvKQ": 8,
        "KNPPvKQN": 7,
        "KBBPPvKP": 7,
        "KBPPvKQN": 5,
        "KRBBPvKR": 5,
        "KRRPvKBP": 5,
        "KRBNvKNP": 5,
        "KQBNPvKQ": 4,
        "KNNPPvKP": 4,
        "KBPPvKQB": 4,
        "KNPPvKQB": 4,
        "KRNPPvKB": 3,
        "KRBNvKBP": 3,
        "KNPPPPvK": 2,
        "KQRPvKRB": 2,
        "KBNPvKQR": 2,
        "KRRNvKRP": 2,
        "KRBBvKNP": 2,
        "KQBPvKBN": 1,
        "KRNNvKNP": 1,
        "KQNPvKNN": 1,
        "KRBNvKQQ": 1,
        "KBNNvKPP": 1,
        "KRNNvKQQ": 1,
        "KBBNPvKB": 1,
        "KBNNPvKB": 1,
        "KRNNPvKR": 1,
        "KQRPvKRN": 1,
        "KQRNvKQP": 1,
        "KQQPvKQB": 1,
        "KQPPvKPP": 135,
        "KRNPPvKP": 33,
        "KRBPPvKP": 31,
        "KRPPPPvK": 14,
        "KQRPvKRP": 11,
        "KQQPvKQP": 10,
        "KRRPvKPP": 9,
        "KBNPPPvK": 9,
        "KNPPvKQR": 7,
        "KQBPvKNP": 6,
        "KQNPvKBP": 6,
        "KQNPvKNP": 6,
        "KRRBPvKR": 5,
        "KPPPvKQN": 5,
        "KQPPPvKN": 4,
        "KQPPPvKB": 4,
        "KQBPvKBP": 3,
        "KBBPPPvK": 3,
        "KQBPPvKR": 3,
        "KQBNvKRP": 2,
        "KPPPvKQB": 2,
        "KBPPvKQR": 2,
        "KRBBPvKN": 2,
        "KQNPPvKR": 2,
        "KRBBvKPP": 1,
        "KQRBvKRN": 1,
        "KRNPvKQQ": 1,
        "KRRPPvKB": 1,
        "KBBNPvKP": 1,
        "KRRPPvKN": 1,
        "KRRNPvKR": 1,
        "KQRNPvKQ": 1,
        "KQRBvKRB": 1,
        "KRBNvKPP": 1,
        "KRBNPvKN": 1,
        "KRNNvKPP": 1,
        "KNNPPPvK": 1,
        "KRBNPvKB": 1,
        "KQPPPvKP": 47,
        "KQNPvKPP": 18,
        "KRBPPPvK": 14,
        "KQBPvKPP": 13,
        "KRRPPvKP": 11,
        "KRNPPPvK": 7,
        "KQBPPvKN": 4,
        "KQRPPvKR": 4,
        "KQRPvKNP": 3,
        "KPPPvKQR": 3,
        "KRBNPvKP": 2,
        "KQBNvKBP": 2,
        "KQQPPvKQ": 2,
        "KBBNPPvK": 2,
        "KQQBvKQP": 1,
        "KQRPvKBP": 1,
        "KQNPPvKN": 1,
        "KQRRPvKQ": 1,
        "KRRNvKPP": 1,
        "KQRRvKRN": 1,
        "KQBPPvKB": 1,
        "KQRBvKRP": 1,
        "KRBBPvKP": 1,
        "KQRPvKPP": 23,
        "KQBPPvKP": 23,
        "KQPPPPvK": 15,
        "KQNPPvKP": 13,
        "KRRPPPvK": 5,
        "KQQPvKRP": 3,
        "KRNNPPvK": 2,
        "KQBNPvKB": 2,
        "KQBNvKPP": 2,
        "KQRBPvKR": 2,
        "KRBNPPvK": 2,
        "KQRPPvKB": 1,
        "KQBBPvKB": 1,
        "KRBBPPvK": 1,
        "KQRNvKNP": 1,
        "KBPPvKQQ": 1,
        "KQRBvKBP": 1,
        "KQRPPvKN": 1,
        "KRRBPvKP": 1,
        "KQRNPvKR": 1,
        "KQRPPvKP": 23,
        "KQBPPPvK": 8,
        "KQNPPPvK": 7,
        "KQBNPvKP": 5,
        "KPPPvKQQ": 2,
        "KQRNvKPP": 2,
        "KRRBPPvK": 2,
        "KQRBvKPP": 2,
        "KQRNPvKN": 1,
        "KQRBPvKB": 1,
        "KQQPvKBP": 1,
        "KRBBNPvK": 1,
        "KQQPPvKR": 1,
        "KQRRPvKR": 1,
        "KQQPvKNP": 1,
        "KQRPPPvK": 4,
        "KQQPvKPP": 3,
        "KQRNPvKP": 3,
        "KQBNPPvK": 3,
        "KQRBPvKP": 2,
        "KQQPPvKN": 1,
        "KQRBPPvK": 5,
        "KQQPPvKP": 4,
        "KQRRPvKP": 2,
        "KQQNvKPP": 1,
        "KQRNPPvK": 1,
        "KQRNNvKP": 1,
        "KQQBPvKP": 3,
        "KQQRPvKP": 1,
        "KQQNPPvK": 1,
        "KQQQPPvK": 1,
        "KQQQBPvK": 1
    },
    "EGTB_most_games": {
        "KRPPvKRP": 37839,
        "KPPPvKPP": 5581,
        "KBPPvKBP": 5429,
        "KNPPvKNP": 4870,
        "KNPPvKBP": 4435,
        "KBPPvKNP": 3926,
        "KQPPvKQP": 3043,
        "KBPPvKRP": 3018,
        "KRBPvKRP": 2279,
        "KRNPvKRP": 2147,
        "KNPPvKRP": 1921,
        "KPPPvKBP": 1711,
        "KPPPvKNP": 1614,
        "KRPPPvKR": 1508,
        "KNPPvKPP": 1481,
        "KPPPvKRP": 1467,
        "KRPPvKRB": 1232,
        "KBPPvKPP": 1138,
        "KRBPvKRB": 1079,
        "KRPPvKRN": 1047,
        "KRPPvKBP": 1012,
        "KRPPvKNP": 802,
        "KRBPvKRN": 799,
        "KRNPvKRN": 719,
        "KRPPvKQP": 715,
        "KRNPvKRB": 685,
        "KRPPvKPP": 676,
        "KBNPvKRP": 596,
        "KBNPvKBP": 436,
        "KBPPPvKR": 431,
        "KQPPPvKQ": 403,
        "KRRPvKRR": 352,
        "KNPPPvKR": 318,
        "KBPPPvKB": 315,
        "KRPPvKBN": 300,
        "KBNPvKNP": 285,
        "KRBPvKQP": 274,
        "KNPPPvKN": 269,
        "KBNPPvKR": 240,
        "KPPPPvKR": 228,
        "KRBPPvKR": 225,
        "KRNPPvKR": 225,
        "KQPPvKRP": 216,
        "KBBPvKBP": 211,
        "KQBPvKQP": 201,
        "KRNPvKQP": 197,
        "KRPPvKRR": 169,
        "KBPPPvKN": 167,
        "KQNPvKQP": 156,
        "KNPPPvKB": 153,
        "KBBPvKRP": 152,
        "KRBPvKRR": 148,
        "KRRPvKQP": 144,
        "KQPPvKRR": 141,
        "KQPPvKPP": 135,
        "KRRPvKRN": 130,
        "KPPPvKQP": 129,
        "KPPPPvKP": 126,
        "KRRPvKRB": 125,
        "KPPPPvKB": 121,
        "KBNPvKPP": 111,
        "KRRPvKRP": 110,
        "KRRPPvKQ": 109,
        "KQPPvKRB": 109,
        "KRPPPvKQ": 104,
        "KNNPvKNP": 101,
        "KRPPPvKP": 101,
        "KNPPPvKP": 100,
        "KBPPPvKP": 99,
        "KRNPvKRR": 99,
        "KRBPPvKQ": 98,
        "KBPPvKRB": 98,
        "KBNPvKBN": 97,
        "KNNPvKRP": 96,
        "KQPPvKQB": 94,
        "KNPPvKRB": 92,
        "KNPPvKQP": 84,
        "KNPPvKBN": 84,
        "KBPPvKBN": 83,
        "KPPPPvKN": 80,
        "KNNPvKBP": 79,
        "KPPPvKBN": 78,
        "KBBPvKBN": 75,
        "KNPPvKRN": 73,
        "KQPPvKRN": 73,
        "KBNPvKRB": 73,
        "KRNPvKNP": 73,
        "KBNPvKQP": 72,
        "KRNPPvKQ": 71,
        "KRBPvKNP": 70,
        "KRBPvKBN": 69,
        "KBPPvKRN": 69,
        "KQPPvKQN": 67,
        "KBPPvKQP": 63,
        "KRNPvKPP": 62,
        "KRBPvKBP": 57,
        "KRBNvKRP": 53,
        "KRNPvKBP": 53,
        "KBBPvKNP": 53,
        "KQRPvKQP": 50,
        "KRPPvKNN": 49,
        "KRBPvKPP": 49,
        "KNNPPvKR": 47,
        "KQPPvKNP": 47,
        "KQPPPvKP": 47,
        "KNPPvKBB": 45,
        "KRBNPvKQ": 42,
        "KQBPvKQB": 41,
        "KQBPPvKQ": 41,
        "KPPPvKRN": 40,
        "KQNPvKQB": 38,
        "KBPPvKBB": 38,
        "KPPPvKRB": 37,
        "KRPPvKBB": 37,
        "KRBNvKQP": 34,
        "KQRPvKQR": 34,
        "KNNPvKPP": 34,
        "KNPPvKNN": 34,
        "KBNPPvKP": 34,
        "KBPPPvKQ": 33,
        "KRNPPvKP": 33,
        "KRNPvKBN": 32,
        "KQPPvKBP": 32,
        "KBNPPvKB": 31,
        "KRBPPvKP": 31,
        "KBNPPvKN": 31,
        "KBBPPvKR": 30,
        "KRRPPvKR": 30,
        "KQNPvKQN": 30,
        "KQPPvKQR": 28,
        "KBNPvKBB": 28,
        "KBNPvKRN": 28,
        "KRPPPvKN": 28,
        "KQNPPvKQ": 27,
        "KQBPvKQN": 26,
        "KNPPPvKQ": 26,
        "KBNPPvKQ": 25,
        "KBNPvKNN": 25,
        "KRNNvKRP": 25,
        "KNNPvKBN": 25,
        "KRBNvKRB": 24,
        "KPPPvKNN": 24,
        "KRBPvKNN": 23,
        "KQRPvKPP": 23,
        "KQRPPvKP": 23,
        "KQBPPvKP": 23,
        "KPPPPvKQ": 22,
        "KNPPvKRR": 21,
        "KRPPvKQR": 20,
        "KQNPvKQR": 19,
        "KBBPvKQP": 19,
        "KRNPPvKN": 18,
        "KQNPvKPP": 18,
        "KRBNPvKR": 18,
        "KRBPvKQB": 17,
        "KQRPvKQB": 17,
        "KRPPPvKB": 17,
        "KRRBvKQP": 17,
        "KBBPvKRB": 17,
        "KRBPvKBB": 16,
        "KQPPvKQQ": 16,
        "KRBNvKRN": 16,
        "KQBPvKQR": 16,
        "KQBPvKRP": 16,
        "KRPPvKQB": 15,
        "KQPPPPvK": 15,
        "KBBNvKRP": 14,
        "KQPPPvKR": 14,
        "KQRPvKQN": 14,
        "KRPPPPvK": 14,
        "KRBPPPvK": 14,
        "KRNPvKBB": 13,
        "KNNPvKRN": 13,
        "KQBPvKPP": 13,
        "KQNPPvKP": 13,
        "KRRBvKRR": 12,
        "KNNPPvKN": 12,
        "KRBPPvKB": 12,
        "KBPPvKRR": 12,
        "KQNPvKRP": 11,
        "KBBPvKRN": 11,
        "KQRPvKRP": 11,
        "KPPPPPvK": 11,
        "KRRPPvKP": 11,
        "KPPPvKBB": 11,
        "KRBBvKRB": 10,
        "KNNPvKQP": 10,
        "KBPPvKNN": 10,
        "KPPPvKRR": 10,
        "KRRNvKRR": 10,
        "KQQPvKQP": 10,
        "KQBPvKRB": 10,
        "KRBPPvKN": 9,
        "KRBBPvKQ": 9,
        "KRRPvKPP": 9,
        "KRBBvKQP": 9,
        "KQBPvKRR": 9,
        "KRRPvKNP": 9,
        "KBBPvKPP": 9,
        "KNNPvKRB": 9,
        "KRRBPvKQ": 9,
        "KBBPPvKB": 9,
        "KBNPPPvK": 9,
        "KBBPvKBB": 8,
        "KBPPPPvK": 8,
        "KQRPPvKQ": 8,
        "KQBPPPvK": 8,
        "KRNPvKQN": 8,
        "KRRNPvKQ": 7,
        "KNNPvKNN": 7,
        "KRNPvKQB": 7,
        "KBNNvKRP": 7,
        "KBNPvKRR": 7,
        "KNPPvKQN": 7,
        "KRBPvKQN": 7,
        "KRNPPPvK": 7,
        "KRBPvKQR": 7,
        "KBBNvKBP": 7,
        "KQNPPPvK": 7,
        "KBBPPvKP": 7,
        "KNPPvKQR": 7,
        "KQBPvKNP": 6,
        "KRPPvKQN": 6,
        "KRNPvKQR": 6,
        "KRNNPvKQ": 6,
        "KRRNvKQP": 6,
        "KRRPvKQR": 6,
        "KQNPvKBP": 6,
        "KRNPvKNN": 6,
        "KQBPvKQQ": 6,
        "KQNPvKNP": 6,
        "KRRBPvKR": 5,
        "KBPPvKQN": 5,
        "KNNPPvKQ": 5,
        "KBBNPvKQ": 5,
        "KRBBPvKR": 5,
        "KPPPvKQN": 5,
        "KRRPvKQB": 5,
        "KBNNvKBP": 5,
        "KNNPPvKB": 5,
        "KRRPvKBP": 5,
        "KRNNvKQP": 5,
        "KQRBPPvK": 5,
        "KQBNPvKP": 5,
        "KQBPvKRN": 5,
        "KRBNvKNP": 5,
        "KRRPPPvK": 5,
        "KBBPvKNN": 4,
        "KQPPPvKN": 4,
        "KQBNPvKQ": 4,
        "KNNPPvKP": 4,
        "KQQPvKQQ": 4,
        "KRNNvKRB": 4,
        "KBNNPvKR": 4,
        "KQNPvKRN": 4,
        "KBPPvKQB": 4,
        "KQBPPvKN": 4,
        "KQNNvKQP": 4,
        "KQQPPvKP": 4,
        "KNPPvKQB": 4,
        "KBBPPvKQ": 4,
        "KRBNvKRR": 4,
        "KQRPPvKR": 4,
        "KQPPPvKB": 4,
        "KQRPPPvK": 4,
        "KBBNvKBN": 3,
        "KRBBvKRP": 3,
        "KRNPPvKB": 3,
        "KQNPvKRR": 3,
        "KNNPvKBB": 3,
        "KQBPvKBP": 3,
        "KQQPvKRP": 3,
        "KBNNvKNN": 3,
        "KQQPvKPP": 3,
        "KQRPvKNP": 3,
        "KQRBvKQR": 3,
        "KQRPvKRR": 3,
        "KBBPPPvK": 3,
        "KBBNPvKR": 3,
        "KQBPPvKR": 3,
        "KQQBPvKP": 3,
        "KBBNvKQP": 3,
        "KRBNvKBP": 3,
        "KPPPvKQR": 3,
        "KQRNPvKP": 3,
        "KQNPvKRB": 3,
        "KQBNPPvK": 3,
        "KQBNvKRP": 2,
        "KRBBvKRN": 2,
        "KPPPvKQB": 2,
        "KBNPvKQB": 2,
        "KBPPvKQR": 2,
        "KNPPPPvK": 2,
        "KRBNvKQB": 2,
        "KPPPvKQQ": 2,
        "KQBBvKQP": 2,
        "KQPPvKNN": 2,
        "KQRPvKRB": 2,
        "KQNPvKQQ": 2,
        "KQRNvKPP": 2,
        "KRNNPPvK": 2,
        "KRBNPvKP": 2,
        "KBNPvKQR": 2,
        "KRNNvKRR": 2,
        "KBNPvKQN": 2,
        "KBNNPvKQ": 2,
        "KNNPvKRR": 2,
        "KQBNPvKB": 2,
        "KQBNvKPP": 2,
        "KQBNvKQP": 2,
        "KBBNvKRB": 2,
        "KQBNvKBP": 2,
        "KBBPvKRR": 2,
        "KQQPPvKQ": 2,
        "KQRBPvKR": 2,
        "KRBBPvKN": 2,
        "KRBNPPvK": 2,
        "KRRNvKRP": 2,
        "KRBBvKNP": 2,
        "KBBPPvKN": 2,
        "KBBNPPvK": 2,
        "KRRBPPvK": 2,
        "KQNPPvKR": 2,
        "KQRBPvKP": 2,
        "KQRBvKPP": 2,
        "KQRRPvKP": 2,
        "KRBBvKRR": 1,
        "KRBBvKPP": 1,
        "KQQPvKQR": 1,
        "KQBPvKBN": 1,
        "KBNNvKBN": 1,
        "KBBNvKRR": 1,
        "KQRBvKQQ": 1,
        "KQQBvKQP": 1,
        "KQRBvKRN": 1,
        "KRNNvKRN": 1,
        "KRNPvKQQ": 1,
        "KQRNvKQN": 1,
        "KRNNvKNP": 1,
        "KBNNvKNP": 1,
        "KQQNvKPP": 1,
        "KRRPPvKB": 1,
        "KBBNPvKP": 1,
        "KQNPvKNN": 1,
        "KQRPPvKB": 1,
        "KRBNvKQQ": 1,
        "KQBBPvKB": 1,
        "KQRNPvKN": 1,
        "KBNNvKPP": 1,
        "KRBNvKQR": 1,
        "KRRBvKQN": 1,
        "KNNPvKQN": 1,
        "KQRBPvKB": 1,
        "KNNPvKQB": 1,
        "KNNNvKRN": 1,
        "KRBBPPvK": 1,
        "KRRPvKQN": 1,
        "KQPPvKBN": 1,
        "KRRPPvKN": 1,
        "KQNNvKQB": 1,
        "KRNNvKQQ": 1,
        "KQRNvKNP": 1,
        "KRBNvKQN": 1,
        "KBNNvKQB": 1,
        "KBBNPvKB": 1,
        "KQRNvKQR": 1,
        "KQRPvKBP": 1,
        "KQQQPPvK": 1,
        "KBPPvKQQ": 1,
        "KQNPPvKN": 1,
        "KBNNPvKB": 1,
        "KBNNvKQP": 1,
        "KRRNPvKR": 1,
        "KRNNPvKR": 1,
        "KBBNvKNP": 1,
        "KQQPvKBP": 1,
        "KQQQBPvK": 1,
        "KQRPvKRN": 1,
        "KQRNPvKQ": 1,
        "KQRBvKRB": 1,
        "KQRBvKBP": 1,
        "KQRPPvKN": 1,
        "KRBNvKPP": 1,
        "KRBNPvKN": 1,
        "KQRRPvKQ": 1,
        "KBBNvKBB": 1,
        "KRBBNPvK": 1,
        "KRRNvKPP": 1,
        "KQQRPvKP": 1,
        "KQQNPPvK": 1,
        "KQRRvKRN": 1,
        "KRRBPvKP": 1,
        "KQRNvKQP": 1,
        "KQRNPPvK": 1,
        "KRNNvKPP": 1,
        "KQRNPvKR": 1,
        "KQRNNvKP": 1,
        "KQQPPvKR": 1,
        "KQBPPvKB": 1,
        "KQPPvKBB": 1,
        "KNNPPPvK": 1,
        "KQRBvKRP": 1,
        "KRBNPvKB": 1,
        "KQQPPvKN": 1,
        "KQRRPvKR": 1,
        "KQQPvKNP": 1,
        "KRBBPvKP": 1,
        "KQQPvKQB": 1
    }
}